iotics/__init__.py
iotics/api/common_pb2.py
iotics/api/common_pb2.pyi
iotics/api/common_pb2_grpc.py
iotics/api/common_pb2_grpc.pyi
iotics/api/feed_pb2.py
iotics/api/feed_pb2.pyi
iotics/api/feed_pb2_grpc.py
iotics/api/feed_pb2_grpc.pyi
iotics/api/host_pb2.py
iotics/api/host_pb2.pyi
iotics/api/host_pb2_grpc.py
iotics/api/host_pb2_grpc.pyi
iotics/api/input_pb2.py
iotics/api/input_pb2.pyi
iotics/api/input_pb2_grpc.py
iotics/api/input_pb2_grpc.pyi
iotics/api/interest_pb2.py
iotics/api/interest_pb2.pyi
iotics/api/interest_pb2_grpc.py
iotics/api/interest_pb2_grpc.pyi
iotics/api/meta_pb2.py
iotics/api/meta_pb2.pyi
iotics/api/meta_pb2_grpc.py
iotics/api/meta_pb2_grpc.pyi
iotics/api/search_pb2.py
iotics/api/search_pb2.pyi
iotics/api/search_pb2_grpc.py
iotics/api/search_pb2_grpc.pyi
iotics/api/twin_pb2.py
iotics/api/twin_pb2.pyi
iotics/api/twin_pb2_grpc.py
iotics/api/twin_pb2_grpc.pyi
iotics/lib/__init__.py
iotics/lib/grpc/__init__.py
iotics/lib/grpc/auth.py
iotics/lib/grpc/base.py
iotics/lib/grpc/feeds.py
iotics/lib/grpc/helpers.py
iotics/lib/grpc/host.py
iotics/lib/grpc/input.py
iotics/lib/grpc/interest.py
iotics/lib/grpc/iotics_api.py
iotics/lib/grpc/search.py
iotics/lib/grpc/sparql.py
iotics/lib/grpc/twins.py
iotics_grpc_client-8.0.0.dist-info/LICENSE
iotics_grpc_client-8.0.0.dist-info/METADATA
iotics_grpc_client-8.0.0.dist-info/WHEEL
iotics_grpc_client-8.0.0.dist-info/top_level.txt
iotics_grpc_client-8.0.0.dist-info/zip-safe
iotics_grpc_client-8.0.0.dist-info/RECORD
