Metadata-Version: 2.1
Name: iotics-grpc-client
Version: 8.0.0
Summary: Iotics gRPC client library
Home-page: https://github.com/Iotic-Labs/iotics-grpc-client-py
Author: Iotics
License: UNKNOWN
Project-URL: Bug Tracker, https://github.com/Iotic-Labs/iotics-grpc-client-py/issues
Project-URL: Changelog, https://github.com/Iotic-Labs/iotics-grpc-client-py/releases
Keywords: iotics,grpc,digital twin
Platform: any
Classifier: Intended Audience :: Developers
Classifier: License :: OSI Approved :: Apache Software License
Classifier: Operating System :: OS Independent
Classifier: Programming Language :: Python
Classifier: Programming Language :: Python :: 3.8
Classifier: Programming Language :: Python :: 3.9
Classifier: Topic :: Software Development :: Libraries :: Python Modules
Requires-Dist: googleapis-common-protos (>=1.56.3)
Requires-Dist: grpcio (>=1.50.0)
Provides-Extra: dev
Requires-Dist: mypy-protobuf (>=3.2.0) ; extra == 'dev'
Requires-Dist: python-dotenv (>=0.20.0) ; extra == 'dev'
Requires-Dist: iotics-identity (>=1.0.4) ; extra == 'dev'
